wydyf/__init__.py
wydyf/__main__.py
wydyf/account.py
wydyf/constants.py
wydyf/feedback.py
wydyf/hours.py
wydyf-0.1.1.dist-info/LICENSE
wydyf-0.1.1.dist-info/METADATA
wydyf-0.1.1.dist-info/WHEEL
wydyf-0.1.1.dist-info/entry_points.txt
wydyf-0.1.1.dist-info/RECORD
